youtube_trending_mcp/__init__.py
youtube_trending_mcp/__main__.py
youtube_trending_mcp/database.py
youtube_trending_mcp/filters.py
youtube_trending_mcp/rss_collector.py
youtube_trending_mcp/server.py
youtube_trending_mcp/validators.py
youtube_trending_mcp/ytdlp_collector.py
youtube_trending_mcp-1.0.0.dist-info/licenses/LICENSE
youtube_trending_mcp-1.0.0.dist-info/METADATA
youtube_trending_mcp-1.0.0.dist-info/WHEEL
youtube_trending_mcp-1.0.0.dist-info/entry_points.txt
youtube_trending_mcp-1.0.0.dist-info/top_level.txt
youtube_trending_mcp-1.0.0.dist-info/RECORD
