Metadata-Version: 2.4
Name: youtube-trending-mcp
Version: 1.0.0
Summary: MCP server for collecting trending YouTube videos without web scraping
Author: AIKONG2024
License: MIT
Project-URL: Homepage, https://github.com/AIKONG2024/youtube-trending-mcp
Project-URL: Repository, https://github.com/AIKONG2024/youtube-trending-mcp
Project-URL: Issues, https://github.com/AIKONG2024/youtube-trending-mcp/issues
Keywords: mcp,youtube,trending,yt-dlp,claude,fastmcp
Classifier: Development Status :: 4 - Beta
Classifier: Intended Audience :: Developers
Classifier: License :: OSI Approved :: MIT License
Classifier: Programming Language :: Python :: 3.10
Classifier: Programming Language :: Python :: 3.11
Classifier: Programming Language :: Python :: 3.12
Requires-Python: >=3.10
License-File: LICENSE
Requires-Dist: mcp>=1.0.0
Requires-Dist: yt-dlp>=2024.11.0
Requires-Dist: feedparser>=6.0.0
Requires-Dist: pyyaml>=6.0.0
Requires-Dist: pydantic>=2.0.0
Provides-Extra: dev
Requires-Dist: pytest>=7.0.0; extra == "dev"
Requires-Dist: pytest-asyncio>=0.21.0; extra == "dev"
Requires-Dist: pytest-cov>=4.0.0; extra == "dev"
Requires-Dist: black>=23.0.0; extra == "dev"
Requires-Dist: ruff>=0.1.0; extra == "dev"
Requires-Dist: mypy>=1.0.0; extra == "dev"
Dynamic: license-file
